{"archives": ["Sîn-tabni", "Šumāya", "Murašû", "Sîn-nāṣir", "Ea-eppēš-ilī A (Babylon)", "Rabâ-ša-Ninurta", "Unknown Borsippa", "Gahal (Babylon)", "Dullupu", "Sîn-ilī (Babylon)", "Egibi Nūr-Sîn", "Gallābu (Ur)", "Atkuppu", "Ea-ilūtu-bāni, Ilī-bāni, Nanāhu", "Ṣāhit-ginê A", "Rē’i-alpi (Borsippa)", "Ilšu-abūšu B", "Ibnāya A", "Iššar-tarībi", "Bēlia’u", "Nappāhu", "Bēl-ušallim//Ingallēa", "Nidinti-Ea", "Ilia A+B", "Sîn-ilī (Ur)", "Esagilāya A", "Ilia D", "Imbia", "Ibnāya B-C-D", "Šangû-Ninurta", "Ea-eppēš-ilī B (Babylon)", "Šamšēa", "Šangû-Šamaš A", "Balāṭu, slave of Rēmūt-Bēl", "fInṣabtu//Naggāru", "Sîn-uballiṭ", "Esagilāya B", "Šumu-iddin/Aplāya", "Ilšu-abūšu A", "Balīhû"], "pre_dated": [19, 13, 88, 24, 47, 12, 10, 11, 15, 142, 1360, 36, 101, 261, 150, 329, 12, 33, 18, 27, 185, 10, 10, 194, 8, 17, 33, 12, 19, 7, 14, 16, 72, 9, 7, 26, 20, 1, 5, 0], "newly_estimated": [0, 0, 6, 2, 6, 2, 2, 2, 3, 32, 296, 8, 24, 64, 36, 80, 3, 9, 6, 10, 73, 4, 4, 82, 4, 9, 20, 10, 11, 5, 9, 14, 80, 10, 8, 34, 25, 10, 23, 19], "unestimatable": [0, 0, 0, 0, 0, 1, 2, 0, 1, 10, 44, 0, 0, 6, 0, 2, 0, 0, 1, 2, 6, 0, 0, 7, 1, 1, 5, 6, 0, 1, 0, 0, 3, 0, 0, 3, 0, 7, 1, 0], "pct_newly_dated": [0.0, 0.0, 6.4, 7.7, 11.3, 13.3, 14.3, 15.4, 15.8, 17.4, 17.4, 18.2, 19.2, 19.3, 19.4, 19.5, 20.0, 21.4, 24.0, 25.6, 27.7, 28.6, 28.6, 29.0, 30.8, 33.3, 34.5, 35.7, 36.7, 38.5, 39.1, 46.7, 51.6, 52.6, 53.3, 54.0, 55.6, 55.6, 79.3, 100.0], "total": [19, 13, 94, 26, 53, 15, 14, 13, 19, 184, 1700, 44, 125, 331, 186, 411, 15, 42, 25, 39, 264, 14, 14, 283, 13, 27, 58, 28, 30, 13, 23, 30, 155, 19, 15, 63, 45, 18, 29, 19]}